[
  {
    "_type": "Politician",
    "uri": "http://watchdog.net/p/daniel_inouye#it",
    "amt_earmark_received": 381149830,
    "amt_earmark_requested": 919270500,
    "bills_sponsored": ["http://watchdog.net/b/us/108/s1084#it", "http://watchdog.net/b/us/108/s1312#it", "http://watchdog.net/b/us/108/s143#it", "http://watchdog.net/b/us/108/s1482#it", "http://watchdog.net/b/us/108/s1565#it", "http://watchdog.net/b/us/108/s1653#it", "http://watchdog.net/b/us/108/s2001#it", "http://watchdog.net/b/us/108/s2097#it", "http://watchdog.net/b/us/108/s2098#it", "http://watchdog.net/b/us/108/s2301#it", "http://watchdog.net/b/us/108/s2382#it", "http://watchdog.net/b/us/108/s2436#it", "http://watchdog.net/b/us/108/s2488#it", "http://watchdog.net/b/us/108/s2489#it", "http://watchdog.net/b/us/108/s2490#it", "http://watchdog.net/b/us/108/s80#it", "http://watchdog.net/b/us/108/s322#it", "http://watchdog.net/b/us/108/s57#it", "http://watchdog.net/b/us/108/s575#it", "http://watchdog.net/b/us/108/s578#it", "http://watchdog.net/b/us/108/s58#it", "http://watchdog.net/b/us/108/s61#it", "http://watchdog.net/b/us/108/s59#it", "http://watchdog.net/b/us/108/s60#it", "http://watchdog.net/b/us/108/s62#it", "http://watchdog.net/b/us/108/s63#it", "http://watchdog.net/b/us/108/s64#it", "http://watchdog.net/b/us/108/s65#it", "http://watchdog.net/b/us/108/s66#it", "http://watchdog.net/b/us/108/s663#it", "http://watchdog.net/b/us/108/s67#it", "http://watchdog.net/b/us/108/s68#it", "http://watchdog.net/b/us/108/s69#it", "http://watchdog.net/b/us/108/s70#it", "http://watchdog.net/b/us/108/s702#it", "http://watchdog.net/b/us/108/s71#it", "http://watchdog.net/b/us/108/s72#it", "http://watchdog.net/b/us/108/s73#it", "http://watchdog.net/b/us/108/s74#it", "http://watchdog.net/b/us/108/s75#it", "http://watchdog.net/b/us/108/s77#it", "http://watchdog.net/b/us/108/s78#it", "http://watchdog.net/b/us/108/s79#it", "http://watchdog.net/b/us/108/s81#it", "http://watchdog.net/b/us/108/s82#it", "http://watchdog.net/b/us/108/s93#it", "http://watchdog.net/b/us/108/s97#it", "http://watchdog.net/b/us/108/s991#it", "http://watchdog.net/b/us/108/sc109#it", "http://watchdog.net/b/us/108/sr107#it", "http://watchdog.net/b/us/108/sr372#it", "http://watchdog.net/b/us/109/s1165#it", "http://watchdog.net/b/us/109/s127#it", "http://watchdog.net/b/us/109/s1390#it", "http://watchdog.net/b/us/109/s146#it", "http://watchdog.net/b/us/109/s1515#it", "http://watchdog.net/b/us/109/s1719#it", "http://watchdog.net/b/us/109/s2135#it", "http://watchdog.net/b/us/109/s215#it", "http://watchdog.net/b/us/109/s216#it", "http://watchdog.net/b/us/109/s2296#it", "http://watchdog.net/b/us/109/s2378#it", "http://watchdog.net/b/us/109/s298#it", "http://watchdog.net/b/us/109/s36#it", "http://watchdog.net/b/us/109/s362#it", "http://watchdog.net/b/us/109/s363#it", "http://watchdog.net/b/us/109/s364#it", "http://watchdog.net/b/us/109/s50#it", "http://watchdog.net/b/us/109/s535#it", "http://watchdog.net/b/us/109/s58#it", "http://watchdog.net/b/us/109/s59#it", "http://watchdog.net/b/us/109/s598#it", "http://watchdog.net/b/us/109/s61#it", "http://watchdog.net/b/us/109/s62#it", "http://watchdog.net/b/us/109/s66#it", "http://watchdog.net/b/us/109/s67#it", "http://watchdog.net/b/us/109/s68#it", "http://watchdog.net/b/us/109/s69#it", "http://watchdog.net/b/us/109/s70#it", "http://watchdog.net/b/us/109/s71#it", "http://watchdog.net/b/us/109/s72#it", "http://watchdog.net/b/us/109/s760#it", "http://watchdog.net/b/us/109/s79#it", "http://watchdog.net/b/us/109/s80#it", "http://watchdog.net/b/us/109/s83#it", "http://watchdog.net/b/us/109/s84#it", "http://watchdog.net/b/us/109/s85#it", "http://watchdog.net/b/us/109/s86#it", "http://watchdog.net/b/us/109/s87#it", "http://watchdog.net/b/us/109/s88#it", "http://watchdog.net/b/us/109/s89#it", "http://watchdog.net/b/us/109/s90#it", "http://watchdog.net/b/us/109/s91#it", "http://watchdog.net/b/us/109/s92#it", "http://watchdog.net/b/us/109/s93#it", "http://watchdog.net/b/us/109/sc72#it", "http://watchdog.net/b/us/109/sr300#it", "http://watchdog.net/b/us/109/sr582#it", "http://watchdog.net/b/us/109/sr9#it", "http://watchdog.net/b/us/110/s1049#it", "http://watchdog.net/b/us/110/s106#it", "http://watchdog.net/b/us/110/s107#it", "http://watchdog.net/b/us/110/s1076#it", "http://watchdog.net/b/us/110/s108#it", "http://watchdog.net/b/us/110/s109#it", "http://watchdog.net/b/us/110/s110#it", "http://watchdog.net/b/us/110/s111#it", "http://watchdog.net/b/us/110/s112#it", "http://watchdog.net/b/us/110/s1319#it", "http://watchdog.net/b/us/110/s1493#it", "http://watchdog.net/b/us/110/s1495#it", "http://watchdog.net/b/us/110/s1583#it", "http://watchdog.net/b/us/110/s1584#it", "http://watchdog.net/b/us/110/s1609#it", "http://watchdog.net/b/us/110/s184#it", "http://watchdog.net/b/us/110/s1852#it", "http://watchdog.net/b/us/110/s2112#it", "http://watchdog.net/b/us/110/s2469#it", "http://watchdog.net/b/us/110/s2579#it", "http://watchdog.net/b/us/110/s2688#it", "http://watchdog.net/b/us/110/s2897#it", "http://watchdog.net/b/us/110/s2907#it", "http://watchdog.net/b/us/110/s3160#it", "http://watchdog.net/b/us/110/s3270#it", "http://watchdog.net/b/us/110/s3598#it", "http://watchdog.net/b/us/110/s429#it", "http://watchdog.net/b/us/110/s53#it", "http://watchdog.net/b/us/110/s54#it", "http://watchdog.net/b/us/110/s56#it", "http://watchdog.net/b/us/110/s57#it", "http://watchdog.net/b/us/110/s58#it", "http://watchdog.net/b/us/110/s59#it", "http://watchdog.net/b/us/110/s60#it", "http://watchdog.net/b/us/110/s61#it", "http://watchdog.net/b/us/110/s62#it", "http://watchdog.net/b/us/110/s63#it", "http://watchdog.net/b/us/110/s64#it", "http://watchdog.net/b/us/110/s66#it", "http://watchdog.net/b/us/110/s67#it", "http://watchdog.net/b/us/110/s70#it", "http://watchdog.net/b/us/110/s71#it", "http://watchdog.net/b/us/110/s710#it", "http://watchdog.net/b/us/110/s72#it", "http://watchdog.net/b/us/110/s73#it", "http://watchdog.net/b/us/110/s890#it", "http://watchdog.net/b/us/110/sr18#it", "http://watchdog.net/b/us/110/sr400#it", "http://watchdog.net/b/us/110/sr58#it", "http://watchdog.net/b/us/111/s112#it", "http://watchdog.net/b/us/111/s113#it", "http://watchdog.net/b/us/111/s114#it", "http://watchdog.net/b/us/111/s50#it", "http://watchdog.net/b/us/111/s51#it", "http://watchdog.net/b/us/111/s52#it", "http://watchdog.net/b/us/111/s53#it", "http://watchdog.net/b/us/111/s54#it", "http://watchdog.net/b/us/111/s55#it", "http://watchdog.net/b/us/111/s56#it", "http://watchdog.net/b/us/111/s57#it", "http://watchdog.net/b/us/111/s58#it", "http://watchdog.net/b/us/111/s59#it", "http://watchdog.net/b/us/111/s63#it", "http://watchdog.net/b/us/111/s65#it", "http://watchdog.net/b/us/111/s66#it", "http://watchdog.net/b/us/111/s67#it", "http://watchdog.net/b/us/111/s68#it", "http://watchdog.net/b/us/111/s69#it", "http://watchdog.net/b/us/111/s70#it", "http://watchdog.net/b/us/111/s72#it", "http://watchdog.net/b/us/111/s76#it", "http://watchdog.net/b/us/111/sr7#it", "http://watchdog.net/b/us/110/s1178#it", "http://watchdog.net/b/us/110/s381#it", "http://watchdog.net/b/us/110/s1580#it", "http://watchdog.net/b/us/110/s385#it", "http://watchdog.net/b/us/110/s509#it", "http://watchdog.net/b/us/110/s1582#it", "http://watchdog.net/b/us/110/s1578#it", "http://watchdog.net/b/us/110/s1492#it"],
    "bioguideid": "I000025",
    "birthday": "09/07/1924",
    "birthplace": "Honolulu, HI",
    "chips2008": null,
    "district": "http://watchdog.net/us/hi#it",
    "earmarks_sponsored": [null, null, null, null, null, null, null, null, null, null, null, null, null, null, null, null, null, null, null, null, null, null, null, null, null, null, null, null, null, null, null, null, null, null, null, null, null, null, null, null, null, null, null, null, null, null, null, null, null, null, null, null, null, null, null, null, null, null, null, null, null, null, null, null, null, null, null, null, null, null, null, null, null, null, null, null, null, null, null, null, null, null, null, null, null, null, null, null, null, null, null, null, null, null, null, null, null, null, null, null, null, null, null, null, null, null, null, null, null, null, null, null, null, null, null, null, null, null, null, null, null, null, null, null, null, null, null, null, null, null, null, null, null, null, null, null, null, null, null, null, null, null, null, null, null, null, null, null, null, null, null, null, null, null, null, null],
    "education": "JD, George Washington University Law School, 1952; BA, Government/Economics, University of Hawaii, 1950.",
    "election_status": "",
    "firstname": "Daniel",
    "gender": "M",
    "govtrackid": "300056",
    "icpsrid": 4812,
    "id": "daniel_inouye",
    "last_elected_year": 2004,
    "lastname": "Inouye",
    "middlename": "K.",
    "money_raised": 1508122,
    "n_bills_cosponsored": 1530,
    "n_bills_debated": 63,
    "n_bills_enacted": 7,
    "n_bills_introduced": 406,
    "n_earmark_received": 127,
    "n_earmark_requested": 156,
    "n_speeches": 15,
    "n_vote_received": 313629,
    "nickname": "",
    "nominate": -0.394,
    "officeurl": "http://inouye.senate.gov/",
    "opensecretsid": "N00001762",
    "party": "Democratic",
    "pct_indiv": 0.5018,
    "pct_instate": 0.0,
    "pct_labor": 0.0,
    "pct_pac": 0.191961,
    "pct_pac_business": null,
    "pct_self": 0.0,
    "pct_smalldonor": 0.0,
    "pct_spent": 0.564148,
    "pct_vote_received": 76.0,
    "photo_credit_text": "Congressional Biographical Directory",
    "photo_credit_url": "http://bioguide.congress.gov/scripts/bibdisplay.pl?index=I000025",
    "photo_path": "/data/crawl/house/photos/I000025.jpg",
    "predictability": 0.95,
    "progressive2008": null,
    "progressiveall": null,
    "religion": "Methodist",
    "votesmartid": "53285",
    "wikipedia": "http://en.wikipedia.org/wiki/Daniel_Inouye",
    "words_per_speech": 1383
  }
]
